bc_devtool/__init__.py
bc_devtool/ali_script.py
bc_devtool/arg_actions.py
bc_devtool/configurator.py
bc_devtool/dev_tools.py
bc_devtool/file_util.py
bc_devtool/op_menu.py
bc_devtool/utils.py
bc_devtool-1.0.3.dist-info/LICENSE
bc_devtool-1.0.3.dist-info/METADATA
bc_devtool-1.0.3.dist-info/WHEEL
bc_devtool-1.0.3.dist-info/entry_points.txt
bc_devtool-1.0.3.dist-info/top_level.txt
bc_devtool-1.0.3.dist-info/RECORD
