Metadata-Version: 2.1
Name: bc-devtool
Version: 1.0.3
Summary: Gadgets to help with development
Home-page: https://github.com/beichenzhizuoshi/bc-devtool
Author: beichenzhizuoshi
Author-email: beichenzhizuoshi@163.com
License: MIT
Classifier: Environment :: Console
Classifier: Intended Audience :: Developers
Classifier: License :: OSI Approved :: MIT License
Classifier: Operating System :: OS Independent
Classifier: Programming Language :: Python :: 3
Classifier: Programming Language :: Python :: 3 :: Only
Requires-Python: >=3.7
License-File: LICENSE
Requires-Dist: GitPython
Requires-Dist: chardet
Requires-Dist: colorama
Requires-Dist: configparser
Requires-Dist: importlib-metadata ; python_version >= "3.7"
